tems/__init__.py
tems/conv_pass.py
tems/py.typed
tems/scale.py
tems/tem.py
tems/umodule.py
tems/unet.py
tems/utils.py
tems-1.0.4.dist-info/licenses/LICENSE
tems-1.0.4.dist-info/METADATA
tems-1.0.4.dist-info/WHEEL
tems-1.0.4.dist-info/top_level.txt
tems-1.0.4.dist-info/RECORD
