Metadata-Version: 2.4
Name: tems
Version: 1.0.4
Summary: Translation Equivariant ModelS
Author-email: William Patton <wllmpttn24@gmail.com>
License: MIT
Project-URL: github, https://github.com/pattonw/tems
Classifier: Programming Language :: Python :: 3
Requires-Python: >=3.11
License-File: LICENSE
Requires-Dist: torch>=2.4
Provides-Extra: dev
Requires-Dist: pytest>=8.3.3; extra == "dev"
Requires-Dist: pytest-cov>=5.0.0; extra == "dev"
Requires-Dist: ruff>=0.6.4; extra == "dev"
Requires-Dist: mypy>=1.11.2; extra == "dev"
Requires-Dist: funlib-persistence>=0.5.0; extra == "dev"
Provides-Extra: docs
Requires-Dist: funlib-learn-torch; extra == "docs"
Requires-Dist: ipykernel>=6.29.5; extra == "docs"
Requires-Dist: nbsphinx>=0.9.6; extra == "docs"
Requires-Dist: sphinx>=8.2.3; extra == "docs"
Requires-Dist: sphinx-autodoc-typehints>=2.0; extra == "docs"
Requires-Dist: sphinx-material>=0.0.36; extra == "docs"
Requires-Dist: sphinx-rtd-theme>=2.0; extra == "docs"
Requires-Dist: myst-parser>=4.0; extra == "docs"
Requires-Dist: jupytext>=1.16.7; extra == "docs"
Dynamic: license-file
